{"grammar_go.md":"4VE32TYT","grammar_might-may.md":"CoqZw2eP","grammar_can-could.md":"unqsQPS8","grammar_get.md":"Cw-EXs3j","grammar_at-on-in.md":"6WJ-xWqs","grammar_infinitive-gerund.md":"B_G-RnOo","grammar_both-either-neither.md":"CKQG3UC4","grammar_must-should-have-to.md":"CJP-zHnV","grammar_as-as-the-same-as.md":"Ba0atz7y","grammar_be-have-do.md":"-Dbnz2lw","movies-tv_family-album-usa_episode14.md":"D1J_9i4_","grammar_intro.md":"BI1gEI2X","phrase_intro.md":"BO93zkLY","grammar_passive-voice.md":"7aKnwiCy","movies-tv_family-album-usa_episode8.md":"D_sTjx91","grammar_no-none-notany.md":"P3uCKwo3","movies-tv_intro.md":"C7cNtaWI","introduce.md":"LmESo7nF","movies-tv_family-album-usa_episode9.md":"VzMEB7By","movies-tv_family-album-usa_episode10.md":"PVmVXBS2","grammar_for-since-ago.md":"DLsNa_gF","grammar_will-shall.md":"DV99UusO","movies-tv_family-album-usa_episode1.md":"DOYbHgNn","phrase_be-going-to.md":"Cmm7DHUx","grammar_too-either-neither.md":"D-mZSYnk","movies-tv_family-album-usa_episode18.md":"DCOohHB-","movies-tv_family-album-usa_episode17.md":"D-_qp_sm","movies-tv_family-album-usa_episode2.md":"C8Ra2FDb","movies-tv_family-album-usa_episode11.md":"CwDSXCYA","movies-tv_family-album-usa_episode19.md":"D6ax_PyE","grammar_part-of-speech.md":"B4dOPHdm","movies-tv_family-album-usa_episode13.md":"CYEFBanI","movies-tv_family-album-usa_episode12.md":"CQWtmw1k","movies-tv_family-album-usa_episode22.md":"UrwItBYU","index.md":"CHARbRdW","movies-tv_family-album-usa_episode5.md":"wXa9g1Kc","movies-tv_family-album-usa_episode20.md":"DBfC02B4","phrase_used-to.md":"BfRMToIU","movies-tv_family-album-usa_episode15.md":"BDMV9xyz","qa_be_devops.md":"DHzlWCAk","movies-tv_family-album-usa_episode25.md":"D-fczQtV","sentence-pattern_sentence-types.md":"Ds_QWkRa","movies-tv_family-album-usa_episode3.md":"CjZFXY9u","qa_web3_contract-security.md":"B86yVAFI","pronunciation_stress.md":"EsFj712O","qa_be_security.md":"DIKgJKe0","tense_past-future.md":"BgfT-OcT","tense_past-simple.md":"nv-LDktL","movies-tv_family-album-usa_episode26.md":"DDn7-WMN","movies-tv_family-album-usa_episode6.md":"BJ-AnQbQ","pronunciation_phonetic-alphabet-classification.md":"BisP_3qw","pronunciation_phoneme.md":"b8Htcvvn","qa_fe_fe-engineering.md":"DFN-nvQe","tense_present-simple.md":"CyKf7PpR","sentence-pattern_sentence-elements.md":"BYGoSM7v","qa_be_performance.md":"BovMzfVk","tense_present-perfect.md":"P17cHxEm","terminology_index.md":"CMoeuH_6","qa_fe_performance-optimization.md":"DczSRh_w","tense_summary.md":"ICLPHgxe","pronunciation_thought-group.md":"yCps0K4E","tense_future-perfect-continuous.md":"M3EYFfri","movies-tv_family-album-usa_episode21.md":"19seL2Sq","sentence-pattern_intro.md":"i5VEWLVt","qa_be_architecture.md":"O66HMpCa","qa_be_distributed-systems.md":"CKLEFWYQ","qa_fe_micro-fe.md":"CSEKGNp7","qa_be_database.md":"BHEcfIoJ","movies-tv_family-album-usa_episode16.md":"BBR6N2hK","qa_interview.md":"BKuxKnA9","qa_web3_development-tools.md":"DUX_Zltt","sentence-pattern_subordinate-clause.md":"CGKNWsDW","tense_past-perfect.md":"B1Ub6no8","qa_web3_frontend-integration.md":"m1qfMETt","movies-tv_family-album-usa_episode23.md":"BBiMO9-m","qa_web3_dapp-architecture.md":"D8O-09uN","tense_future-continuous.md":"WLhfDKVO","tense_intro.md":"BzkpeQFY","tense_future-simple.md":"BUEWK0f9","movies-tv_family-album-usa_episode7.md":"Bkb8TGAq","tense_past-future-continuous.md":"B-w3bfhO","qa_fe_other.md":"RfnEEZtr","qa_fe_lowcode.md":"CuagI30P","qa_fe_css.md":"B5Q0YkB9","qa_web3_smart-contracts.md":"VfkK3A8t","sentence-pattern_common-sentence.md":"q7qmZjLP","qa_fe_security.md":"DH9PsWD_","tense_present-continuous.md":"2Hbg02UI","qa_intro.md":"BjU-GTdr","tense_past-continuous.md":"CeVNE_CH","qa_fe_monitor.md":"DV8KK5eu","movies-tv_family-album-usa_episode24.md":"C5xFkcul","tense_future-perfect.md":"DLylM0GY","phrase_others.md":"Bw3C8ptU","tense_past-future-perfect.md":"ZS9UeX18","tense_past-future-perfect-continuous.md":"BkTSIxbL","qa_be_nodejs.md":"DNQZxl4L","pronunciation_liaison.md":"_d_Vok-q","pronunciation_intro.md":"UVo4Kfe-","tense_present-perfect-continuous.md":"a2Ztm6fH","movies-tv_family-album-usa_episode4.md":"pM2D0Eez","tense_past-perfect-continuous.md":"DUtXke5n","qa_other.md":"CzwPmQmN","qa_fe_cli.md":"m9_82_-k"}
